FinGraph.py
FinGraph-0.1.0.dist-info/LICENSE
FinGraph-0.1.0.dist-info/METADATA
FinGraph-0.1.0.dist-info/WHEEL
FinGraph-0.1.0.dist-info/top_level.txt
FinGraph-0.1.0.dist-info/RECORD
