Metadata-Version: 2.1
Name: FinGraph
Version: 0.1.0
Summary: A simple abstraction layer on top of Matplotlib that allows for easily displaying financial graphics.
Home-page: https://github.com/ctjlewis/FinGraph
Author: C. Lewis
Author-email: ctj.lewis@icloud.com
License: UNKNOWN
Platform: UNKNOWN
Classifier: Programming Language :: Python :: 3
Classifier: License :: OSI Approved :: MIT License
Classifier: Operating System :: OS Independent
License-File: LICENSE
